custom_nester.py
custom_nester-1.3.0.dist-info/METADATA
custom_nester-1.3.0.dist-info/WHEEL
custom_nester-1.3.0.dist-info/top_level.txt
custom_nester-1.3.0.dist-info/RECORD
