Metadata-Version: 2.1
Name: custom_nester
Version: 1.3.0
Summary: A simple printer of nested lists
Home-page: https://github.com/arielden/
Author: arielden
Author-email: arieldenaro@gmail.com
License: MIT
Classifier: License :: OSI Approved :: MIT License
Classifier: Programming Language :: Python :: 3.9
Classifier: Operating System :: OS Independent
Requires-Python: >=3.9
